can_ada.cp39-win_amd64.pyd
can_ada-stubs/__init__.pyi
can_ada-2.0.0.dist-info/LICENSE
can_ada-2.0.0.dist-info/METADATA
can_ada-2.0.0.dist-info/WHEEL
can_ada-2.0.0.dist-info/top_level.txt
can_ada-2.0.0.dist-info/RECORD
