Metadata-Version: 2.2
Name: can_ada
Version: 2.0.0
Summary: Ada is a fast spec-compliant url parser
Home-page: https://github.com/tktech/can_ada
Author: Tyler Kennedy
Author-email: tk@tkte.ch
License: MIT
Requires-Python: >=3.9
License-File: LICENSE
Provides-Extra: test
Requires-Dist: pytest; extra == "test"
Requires-Dist: pytest-benchmark; extra == "test"
Requires-Dist: ada_url; extra == "test"
Dynamic: author
Dynamic: author-email
Dynamic: description
Dynamic: description-content-type
Dynamic: home-page
Dynamic: license
Dynamic: provides-extra
Dynamic: requires-python
Dynamic: summary
